odoo/addons/purchase_delivery_split_date/README.rst
odoo/addons/purchase_delivery_split_date/__init__.py
odoo/addons/purchase_delivery_split_date/__manifest__.py
odoo/addons/purchase_delivery_split_date/i18n/ca.po
odoo/addons/purchase_delivery_split_date/i18n/de.po
odoo/addons/purchase_delivery_split_date/i18n/es.po
odoo/addons/purchase_delivery_split_date/i18n/es_MX.po
odoo/addons/purchase_delivery_split_date/i18n/es_PE.po
odoo/addons/purchase_delivery_split_date/i18n/fi.po
odoo/addons/purchase_delivery_split_date/i18n/fr.po
odoo/addons/purchase_delivery_split_date/i18n/gl.po
odoo/addons/purchase_delivery_split_date/i18n/hr.po
odoo/addons/purchase_delivery_split_date/i18n/it.po
odoo/addons/purchase_delivery_split_date/i18n/nl_NL.po
odoo/addons/purchase_delivery_split_date/i18n/pt_BR.po
odoo/addons/purchase_delivery_split_date/i18n/pt_PT.po
odoo/addons/purchase_delivery_split_date/i18n/purchase_delivery_split_date.pot
odoo/addons/purchase_delivery_split_date/i18n/ro.po
odoo/addons/purchase_delivery_split_date/i18n/sl.po
odoo/addons/purchase_delivery_split_date/i18n/zh_CN.po
odoo/addons/purchase_delivery_split_date/models/__init__.py
odoo/addons/purchase_delivery_split_date/models/purchase_order_line.py
odoo/addons/purchase_delivery_split_date/models/stock_move.py
odoo/addons/purchase_delivery_split_date/models/stock_picking.py
odoo/addons/purchase_delivery_split_date/readme/CONTRIBUTORS.md
odoo/addons/purchase_delivery_split_date/readme/DESCRIPTION.md
odoo/addons/purchase_delivery_split_date/readme/HISTORY.md
odoo/addons/purchase_delivery_split_date/readme/USAGE.md
odoo/addons/purchase_delivery_split_date/static/description/icon.png
odoo/addons/purchase_delivery_split_date/static/description/index.html
odoo/addons/purchase_delivery_split_date/static/description/split_delivery.png
odoo/addons/purchase_delivery_split_date/tests/__init__.py
odoo/addons/purchase_delivery_split_date/tests/test_purchase_delivery.py
odoo_addon_purchase_delivery_split_date-18.0.2.0.3.dist-info/METADATA
odoo_addon_purchase_delivery_split_date-18.0.2.0.3.dist-info/WHEEL
odoo_addon_purchase_delivery_split_date-18.0.2.0.3.dist-info/top_level.txt
odoo_addon_purchase_delivery_split_date-18.0.2.0.3.dist-info/RECORD
