Metadata-Version: 2.1
Name: odoo-addon-purchase_delivery_split_date
Version: 18.0.2.0.3
Requires-Python: >=3.10
Requires-Dist: odoo==18.0.*
Summary: Allows Purchase Order you confirm to generate one Incoming Shipment for each expected date indicated in the Purchase Order Lines
Home-page: https://github.com/OCA/purchase-workflow
License: AGPL-3
Author: Numerigraphe, ForgeFlow, Camptocamp, BCIM, Odoo Community Association (OCA)
Author-email: support@odoo-community.org
Classifier: Programming Language :: Python
Classifier: Framework :: Odoo
Classifier: Framework :: Odoo :: 18.0
Classifier: License :: OSI Approved :: GNU Affero General Public License v3
